CRSPcleaner.py
CRSPcleaner-0.0.1.dist-info/METADATA
CRSPcleaner-0.0.1.dist-info/WHEEL
CRSPcleaner-0.0.1.dist-info/top_level.txt
CRSPcleaner-0.0.1.dist-info/RECORD
