Metadata-Version: 2.1
Name: CRSPcleaner
Version: 0.0.1
Summary: Cleans a CRSP .csv database and returns it as a Pandas Dataframe
Home-page: https://vash.uk/python-for-finance/
Author: Vashisht Bhatt
Author-email: info@vash.uk
License: MIT
Platform: UNKNOWN
Classifier: Development Status :: 4 - Beta
Classifier: License :: OSI Approved :: MIT License
Classifier: Programming Language :: Python :: 3.7
Requires-Dist: pandas
Requires-Dist: numpy
Requires-Dist: dateutil
